README.md
setup.py
gisce/__init__.py
gisce/base.py
gisce/compat.py
gisce/msgpack.py
gisce/restapi.py
gisce/xmlprc_wst.py
gisce/xmlrpc.py
pygisceclient.egg-info/PKG-INFO
pygisceclient.egg-info/SOURCES.txt
pygisceclient.egg-info/dependency_links.txt
pygisceclient.egg-info/requires.txt
pygisceclient.egg-info/top_level.txt
tests/__init__.py
tests/test_request_id.py
tests/test_xmlrpc_request_id.py