Metadata-Version: 2.4
Name: pygisceclient
Version: 0.9.1
Summary: Python client to access the GISCE ERP
Home-page: https://github.com/gisce/py-gisce-client
Author: GISCE
Author-email: devel@gisce.net
License: General Public Licence 2
Provides: pygisceclient
Requires-Dist: requests
Dynamic: author
Dynamic: author-email
Dynamic: description
Dynamic: home-page
Dynamic: license
Dynamic: provides
Dynamic: requires-dist
Dynamic: summary
